[
    {
        "key": "1468.1.1|monarch|name",
        "original": "Ibak",
        "translation": "",
        "stage": 0
    },
    {
        "key": "1468.1.1|monarch|dynasty",
        "original": "Shaybanid",
        "translation": "昔班尼",
        "stage": 5
    },
    {
        "key": "1495.1.1#|monarch|name",
        "original": "Muhammad",
        "translation": "穆罕默德",
        "stage": 1
    },
    {
        "key": "1495.1.1#|monarch|dynasty",
        "original": "Taibughin",
        "translation": "",
        "stage": 0
    },
    {
        "key": "1495.1.1##|heir|name",
        "original": "Qasim",
        "translation": "卡西姆",
        "stage": 1
    },
    {
        "key": "1495.1.1##|heir|monarch_name",
        "original": "Qasim",
        "translation": "卡西姆",
        "stage": 1
    },
    {
        "key": "1495.1.1##|heir|dynasty",
        "original": "Taibughin",
        "translation": "",
        "stage": 0
    },
    {
        "key": "1530.1.1|monarch|name",
        "original": "Qasim",
        "translation": "卡西姆",
        "stage": 1
    },
    {
        "key": "1530.1.1|monarch|dynasty",
        "original": "Taibughin",
        "translation": "",
        "stage": 0
    },
    {
        "key": "1530.1.1#|heir|name",
        "original": "Edigu",
        "translation": "也迪古",
        "stage": 1
    },
    {
        "key": "1530.1.1#|heir|monarch_name",
        "original": "Edigu",
        "translation": "也迪古",
        "stage": 1
    },
    {
        "key": "1530.1.1#|heir|dynasty",
        "original": "Taibughin",
        "translation": "",
        "stage": 0
    },
    {
        "key": "1550.1.1|monarch|name",
        "original": "Edigu",
        "translation": "也迪古",
        "stage": 1
    },
    {
        "key": "1550.1.1|monarch|dynasty",
        "original": "Taibughin",
        "translation": "",
        "stage": 0
    },
    {
        "key": "1563.1.1|monarch|name",
        "original": "Kuchum",
        "translation": "库楚",
        "stage": 1
    },
    {
        "key": "1563.1.1|monarch|dynasty",
        "original": "Shaybanid",
        "translation": "昔班尼",
        "stage": 5
    },
    {
        "key": "1563.1.1#|heir|name",
        "original": "Ali",
        "translation": "阿里",
        "stage": 1
    },
    {
        "key": "1563.1.1#|heir|monarch_name",
        "original": "Ali",
        "translation": "阿里",
        "stage": 1
    },
    {
        "key": "1563.1.1#|heir|dynasty",
        "original": "Shaybanid",
        "translation": "昔班尼",
        "stage": 5
    },
    {
        "key": "1600.1.1|monarch|name",
        "original": "Ali",
        "translation": "阿里",
        "stage": 1
    },
    {
        "key": "1600.1.1|monarch|dynasty",
        "original": "Shaybanid",
        "translation": "昔班尼",
        "stage": 5
    }
]
