[
    {
        "key": "1377.1.28|monarch|name",
        "original": "Maria I",
        "translation": "玛丽亚 I",
        "stage": 1,
        "file": "history/countries/SIC - Sicily.txt"
    },
    {
        "key": "1377.1.28|monarch|dynasty",
        "original": "d'Aragó",
        "translation": "德 阿拉贡",
        "stage": 1,
        "file": "history/countries/SIC - Sicily.txt"
    },
    {
        "key": "1713.4.12|monarch|name",
        "original": "Vittorio Amedeo II",
        "translation": "维托里奥 阿梅迪奥 II",
        "stage": 1,
        "file": "history/countries/SIC - Sicily.txt"
    },
    {
        "key": "1713.4.12|monarch|dynasty",
        "original": "di Savoia",
        "translation": "迪 萨伏伊",
        "stage": 1,
        "file": "history/countries/SIC - Sicily.txt"
    },
    {
        "key": "1713.4.12|monarch|leader|name",
        "original": "Vittorio Amedeo II",
        "translation": "维托里奥 阿梅迪奥 II",
        "stage": 1,
        "file": "history/countries/SIC - Sicily.txt"
    },
    {
        "key": "1806.3.11#|monarch|name",
        "original": "Ferrante IV",
        "translation": "费兰特 IV",
        "stage": 1,
        "file": "history/countries/SIC - Sicily.txt"
    },
    {
        "key": "1806.3.11#|monarch|dynasty",
        "original": "de Bourbon",
        "translation": "德 波旁",
        "stage": 1,
        "file": "history/countries/SIC - Sicily.txt"
    }
]