[
    {
        "key": "1392.1.1|monarch|name",
        "original": "Eberhard III",
        "translation": "埃伯哈德 III",
        "stage": 5,
        "file": "history/countries/WUR - Wurttemberg.txt"
    },
    {
        "key": "1392.1.1|monarch|dynasty",
        "original": "von Württemberg",
        "translation": "冯 符腾堡",
        "stage": 5,
        "file": "history/countries/WUR - Wurttemberg.txt"
    },
    {
        "key": "1392.1.1#|heir|name",
        "original": "Eberhard",
        "translation": "埃伯哈德",
        "stage": 5,
        "file": "history/countries/WUR - Wurttemberg.txt"
    },
    {
        "key": "1392.1.1#|heir|monarch_name",
        "original": "Eberhard IV",
        "translation": "埃伯哈德 IV",
        "stage": 5,
        "file": "history/countries/WUR - Wurttemberg.txt"
    },
    {
        "key": "1392.1.1#|heir|dynasty",
        "original": "von Württemberg",
        "translation": "冯 符腾堡",
        "stage": 5,
        "file": "history/countries/WUR - Wurttemberg.txt"
    },
    {
        "key": "1417.1.1|monarch|name",
        "original": "Eberhard IV",
        "translation": "埃伯哈德 IV",
        "stage": 5,
        "file": "history/countries/WUR - Wurttemberg.txt"
    },
    {
        "key": "1417.1.1|monarch|dynasty",
        "original": "von Württemberg",
        "translation": "冯 符腾堡",
        "stage": 5,
        "file": "history/countries/WUR - Wurttemberg.txt"
    },
    {
        "key": "1417.1.1#|heir|name",
        "original": "Ulrich",
        "translation": "乌尔里希",
        "stage": 5,
        "file": "history/countries/WUR - Wurttemberg.txt"
    },
    {
        "key": "1417.1.1#|heir|monarch_name",
        "original": "Ulrich V",
        "translation": "乌尔里希 V",
        "stage": 5,
        "file": "history/countries/WUR - Wurttemberg.txt"
    },
    {
        "key": "1417.1.1#|heir|dynasty",
        "original": "von Württmeberg",
        "translation": "冯 符腾堡",
        "stage": 5,
        "file": "history/countries/WUR - Wurttemberg.txt"
    },
    {
        "key": "1419.7.2|monarch|name",
        "original": "Ulrich V",
        "translation": "乌尔里希 V",
        "stage": 5,
        "file": "history/countries/WUR - Wurttemberg.txt"
    },
    {
        "key": "1419.7.2|monarch|dynasty",
        "original": "von Württemberg",
        "translation": "冯 符腾堡",
        "stage": 5,
        "file": "history/countries/WUR - Wurttemberg.txt"
    },
    {
        "key": "1447.2.1|heir|name",
        "original": "Eberhard",
        "translation": "埃伯哈德",
        "stage": 5,
        "file": "history/countries/WUR - Wurttemberg.txt"
    },
    {
        "key": "1447.2.1|heir|monarch_name",
        "original": "Eberhard I",
        "translation": "埃伯哈德 I",
        "stage": 5,
        "file": "history/countries/WUR - Wurttemberg.txt"
    },
    {
        "key": "1447.2.1|heir|dynasty",
        "original": "von Württemberg",
        "translation": "冯 符腾堡",
        "stage": 5,
        "file": "history/countries/WUR - Wurttemberg.txt"
    },
    {
        "key": "1457.1.1|monarch|name",
        "original": "Eberhard I",
        "translation": "埃伯哈德 I",
        "stage": 5,
        "file": "history/countries/WUR - Wurttemberg.txt"
    },
    {
        "key": "1457.1.1|monarch|dynasty",
        "original": "von Württemberg",
        "translation": "冯 符腾堡",
        "stage": 5,
        "file": "history/countries/WUR - Wurttemberg.txt"
    },
    {
        "key": "1457.1.1#|heir|name",
        "original": "Eberhard",
        "translation": "埃伯哈德",
        "stage": 5,
        "file": "history/countries/WUR - Wurttemberg.txt"
    },
    {
        "key": "1457.1.1#|heir|monarch_name",
        "original": "Eberhard II",
        "translation": "埃伯哈德 II",
        "stage": 5,
        "file": "history/countries/WUR - Wurttemberg.txt"
    },
    {
        "key": "1457.1.1#|heir|dynasty",
        "original": "von Württemberg",
        "translation": "冯 符腾堡",
        "stage": 5,
        "file": "history/countries/WUR - Wurttemberg.txt"
    },
    {
        "key": "1496.2.24|monarch|name",
        "original": "Eberhard II",
        "translation": "埃伯哈德 II",
        "stage": 5,
        "file": "history/countries/WUR - Wurttemberg.txt"
    },
    {
        "key": "1496.2.24|monarch|dynasty",
        "original": "von Württemberg",
        "translation": "冯 符腾堡",
        "stage": 5,
        "file": "history/countries/WUR - Wurttemberg.txt"
    },
    {
        "key": "1496.2.24#|heir|name",
        "original": "Ulrich",
        "translation": "乌尔里希",
        "stage": 5,
        "file": "history/countries/WUR - Wurttemberg.txt"
    },
    {
        "key": "1496.2.24#|heir|monarch_name",
        "original": "Ulrich",
        "translation": "乌尔里希",
        "stage": 5,
        "file": "history/countries/WUR - Wurttemberg.txt"
    },
    {
        "key": "1496.2.24#|heir|dynasty",
        "original": "von Württemberg",
        "translation": "冯 符腾堡",
        "stage": 5,
        "file": "history/countries/WUR - Wurttemberg.txt"
    },
    {
        "key": "1498.1.1|monarch|name",
        "original": "Ulrich",
        "translation": "乌尔里希",
        "stage": 5,
        "file": "history/countries/WUR - Wurttemberg.txt"
    },
    {
        "key": "1498.1.1|monarch|dynasty",
        "original": "von Württemberg",
        "translation": "冯 符腾堡",
        "stage": 5,
        "file": "history/countries/WUR - Wurttemberg.txt"
    },
    {
        "key": "1515.5.2|heir|name",
        "original": "Cristoph",
        "translation": "克里斯托夫",
        "stage": 5,
        "file": "history/countries/WUR - Wurttemberg.txt"
    },
    {
        "key": "1515.5.2|heir|monarch_name",
        "original": "Cristoph",
        "translation": "克里斯托夫",
        "stage": 5,
        "file": "history/countries/WUR - Wurttemberg.txt"
    },
    {
        "key": "1515.5.2|heir|dynasty",
        "original": "von Württemberg",
        "translation": "冯 符腾堡",
        "stage": 5,
        "file": "history/countries/WUR - Wurttemberg.txt"
    },
    {
        "key": "1550.1.1|monarch|name",
        "original": "Christoph",
        "translation": "克里斯托夫",
        "stage": 5,
        "file": "history/countries/WUR - Wurttemberg.txt"
    },
    {
        "key": "1550.1.1|monarch|dynasty",
        "original": "von Württemberg",
        "translation": "冯 符腾堡",
        "stage": 5,
        "file": "history/countries/WUR - Wurttemberg.txt"
    },
    {
        "key": "1554.1.1|heir|name",
        "original": "Ludwig",
        "translation": "路德维希",
        "stage": 5,
        "file": "history/countries/WUR - Wurttemberg.txt"
    },
    {
        "key": "1554.1.1|heir|monarch_name",
        "original": "Ludwig der Fromme",
        "translation": "虔诚者 路德维希",
        "stage": 1,
        "file": "history/countries/WUR - Wurttemberg.txt"
    },
    {
        "key": "1554.1.1|heir|dynasty",
        "original": "von Württemberg",
        "translation": "冯 符腾堡",
        "stage": 5,
        "file": "history/countries/WUR - Wurttemberg.txt"
    },
    {
        "key": "1568.12.28|monarch|name",
        "original": "Ludwig der Fromme",
        "translation": "虔诚者 路德维希",
        "stage": 1,
        "file": "history/countries/WUR - Wurttemberg.txt"
    },
    {
        "key": "1568.12.28|monarch|dynasty",
        "original": "von Württemberg",
        "translation": "冯 符腾堡",
        "stage": 5,
        "file": "history/countries/WUR - Wurttemberg.txt"
    },
    {
        "key": "1568.12.28#|heir|name",
        "original": "Friedrich",
        "translation": "弗里德里希",
        "stage": 5,
        "file": "history/countries/WUR - Wurttemberg.txt"
    },
    {
        "key": "1568.12.28#|heir|monarch_name",
        "original": "Friedrich I",
        "translation": "弗里德里希 I",
        "stage": 5,
        "file": "history/countries/WUR - Wurttemberg.txt"
    },
    {
        "key": "1568.12.28#|heir|dynasty",
        "original": "von Württemberg",
        "translation": "冯 符腾堡",
        "stage": 5,
        "file": "history/countries/WUR - Wurttemberg.txt"
    },
    {
        "key": "1593.8.28|monarch|name",
        "original": "Friedrich I",
        "translation": "弗里德里希 I",
        "stage": 5,
        "file": "history/countries/WUR - Wurttemberg.txt"
    },
    {
        "key": "1593.8.28|monarch|dynasty",
        "original": "von Württemberg",
        "translation": "冯 符腾堡",
        "stage": 5,
        "file": "history/countries/WUR - Wurttemberg.txt"
    },
    {
        "key": "1593.8.28#|heir|name",
        "original": "Johann Friedrich",
        "translation": "约翰 弗里德里希",
        "stage": 5,
        "file": "history/countries/WUR - Wurttemberg.txt"
    },
    {
        "key": "1593.8.28#|heir|monarch_name",
        "original": "Johann Friedrich",
        "translation": "约翰 弗里德里希",
        "stage": 5,
        "file": "history/countries/WUR - Wurttemberg.txt"
    },
    {
        "key": "1593.8.28#|heir|dynasty",
        "original": "von Württemberg",
        "translation": "冯 符腾堡",
        "stage": 5,
        "file": "history/countries/WUR - Wurttemberg.txt"
    },
    {
        "key": "1608.1.29|monarch|name",
        "original": "Johann Friedrich",
        "translation": "约翰 弗里德里希",
        "stage": 5,
        "file": "history/countries/WUR - Wurttemberg.txt"
    },
    {
        "key": "1608.1.29|monarch|dynasty",
        "original": "von Württemberg",
        "translation": "冯 符腾堡",
        "stage": 5,
        "file": "history/countries/WUR - Wurttemberg.txt"
    },
    {
        "key": "1614.12.16|heir|name",
        "original": "Eberhard",
        "translation": "埃伯哈德",
        "stage": 5,
        "file": "history/countries/WUR - Wurttemberg.txt"
    },
    {
        "key": "1614.12.16|heir|monarch_name",
        "original": "Eberhard III",
        "translation": "埃伯哈德 III",
        "stage": 5,
        "file": "history/countries/WUR - Wurttemberg.txt"
    },
    {
        "key": "1614.12.16|heir|dynasty",
        "original": "von Württemberg",
        "translation": "冯 符腾堡",
        "stage": 5,
        "file": "history/countries/WUR - Wurttemberg.txt"
    },
    {
        "key": "1628.7.18|monarch|name",
        "original": "Eberhard III",
        "translation": "埃伯哈德 III",
        "stage": 5,
        "file": "history/countries/WUR - Wurttemberg.txt"
    },
    {
        "key": "1628.7.18|monarch|dynasty",
        "original": "von Württemberg",
        "translation": "冯 符腾堡",
        "stage": 5,
        "file": "history/countries/WUR - Wurttemberg.txt"
    },
    {
        "key": "1647.1.7|heir|name",
        "original": "Wilhelm Ludwig",
        "translation": "威廉 路德维希",
        "stage": 5,
        "file": "history/countries/WUR - Wurttemberg.txt"
    },
    {
        "key": "1647.1.7|heir|monarch_name",
        "original": "Wilhelm Ludwig",
        "translation": "威廉 路德维希",
        "stage": 5,
        "file": "history/countries/WUR - Wurttemberg.txt"
    },
    {
        "key": "1647.1.7|heir|dynasty",
        "original": "von Württemberg",
        "translation": "冯 符腾堡",
        "stage": 5,
        "file": "history/countries/WUR - Wurttemberg.txt"
    },
    {
        "key": "1674.7.2|monarch|name",
        "original": "Wilhelm Ludwig",
        "translation": "威廉 路德维希",
        "stage": 5,
        "file": "history/countries/WUR - Wurttemberg.txt"
    },
    {
        "key": "1674.7.2|monarch|dynasty",
        "original": "von Württemberg",
        "translation": "冯 符腾堡",
        "stage": 5,
        "file": "history/countries/WUR - Wurttemberg.txt"
    },
    {
        "key": "1674.7.2#|heir|name",
        "original": "Friedrich Karl",
        "translation": "弗里德里希 卡尔",
        "stage": 5,
        "file": "history/countries/WUR - Wurttemberg.txt"
    },
    {
        "key": "1674.7.2#|heir|monarch_name",
        "original": "Friedrich Karl",
        "translation": "弗里德里希 卡尔",
        "stage": 5,
        "file": "history/countries/WUR - Wurttemberg.txt"
    },
    {
        "key": "1674.7.2#|heir|dynasty",
        "original": "von Württemberg",
        "translation": "冯 符腾堡",
        "stage": 5,
        "file": "history/countries/WUR - Wurttemberg.txt"
    },
    {
        "key": "1677.6.23|monarch|name",
        "original": "Friedrich Karl",
        "translation": "弗里德里希 卡尔",
        "stage": 5,
        "file": "history/countries/WUR - Wurttemberg.txt"
    },
    {
        "key": "1677.6.23|monarch|dynasty",
        "original": "von Württemberg",
        "translation": "冯 符腾堡",
        "stage": 5,
        "file": "history/countries/WUR - Wurttemberg.txt"
    },
    {
        "key": "1677.6.23#|heir|name",
        "original": "Eberhard Ludwig",
        "translation": "埃伯哈德 路德维希",
        "stage": 5,
        "file": "history/countries/WUR - Wurttemberg.txt"
    },
    {
        "key": "1677.6.23#|heir|monarch_name",
        "original": "Eberhard Ludwig",
        "translation": "埃伯哈德 路德维希",
        "stage": 5,
        "file": "history/countries/WUR - Wurttemberg.txt"
    },
    {
        "key": "1677.6.23#|heir|dynasty",
        "original": "von Württemberg",
        "translation": "冯 符腾堡",
        "stage": 5,
        "file": "history/countries/WUR - Wurttemberg.txt"
    },
    {
        "key": "1693.1.22|monarch|name",
        "original": "Eberhard Ludwig",
        "translation": "埃伯哈德 路德维希",
        "stage": 5,
        "file": "history/countries/WUR - Wurttemberg.txt"
    },
    {
        "key": "1693.1.22|monarch|dynasty",
        "original": "von Württemberg",
        "translation": "冯 符腾堡",
        "stage": 5,
        "file": "history/countries/WUR - Wurttemberg.txt"
    },
    {
        "key": "1693.1.22#|heir|name",
        "original": "Karl Alexander",
        "translation": "卡尔 亚历山大",
        "stage": 5,
        "file": "history/countries/WUR - Wurttemberg.txt"
    },
    {
        "key": "1693.1.22#|heir|monarch_name",
        "original": "Karl Alexander",
        "translation": "卡尔 亚历山大",
        "stage": 5,
        "file": "history/countries/WUR - Wurttemberg.txt"
    },
    {
        "key": "1693.1.22#|heir|dynasty",
        "original": "von Württemberg",
        "translation": "冯 符腾堡",
        "stage": 5,
        "file": "history/countries/WUR - Wurttemberg.txt"
    },
    {
        "key": "1733.10.1|monarch|name",
        "original": "Karl Alexander",
        "translation": "卡尔 亚历山大",
        "stage": 5,
        "file": "history/countries/WUR - Wurttemberg.txt"
    },
    {
        "key": "1733.10.1|monarch|dynasty",
        "original": "von Württemberg",
        "translation": "冯 符腾堡",
        "stage": 5,
        "file": "history/countries/WUR - Wurttemberg.txt"
    },
    {
        "key": "1733.10.1#|heir|name",
        "original": "Karl Eugen",
        "translation": "卡尔 欧根",
        "stage": 5,
        "file": "history/countries/WUR - Wurttemberg.txt"
    },
    {
        "key": "1733.10.1#|heir|monarch_name",
        "original": "Karl Eugen",
        "translation": "卡尔 欧根",
        "stage": 5,
        "file": "history/countries/WUR - Wurttemberg.txt"
    },
    {
        "key": "1733.10.1#|heir|dynasty",
        "original": "von Württemberg",
        "translation": "冯 符腾堡",
        "stage": 5,
        "file": "history/countries/WUR - Wurttemberg.txt"
    },
    {
        "key": "1737.3.12|monarch|name",
        "original": "Karl Eugen",
        "translation": "卡尔 欧根",
        "stage": 5,
        "file": "history/countries/WUR - Wurttemberg.txt"
    },
    {
        "key": "1737.3.12|monarch|dynasty",
        "original": "von Württemberg",
        "translation": "冯 符腾堡",
        "stage": 5,
        "file": "history/countries/WUR - Wurttemberg.txt"
    },
    {
        "key": "1737.3.12#|heir|name",
        "original": "Ludwig Eugen",
        "translation": "路德维希 欧根",
        "stage": 5,
        "file": "history/countries/WUR - Wurttemberg.txt"
    },
    {
        "key": "1737.3.12#|heir|monarch_name",
        "original": "Ludwig Eugen",
        "translation": "路德维希 欧根",
        "stage": 5,
        "file": "history/countries/WUR - Wurttemberg.txt"
    },
    {
        "key": "1737.3.12#|heir|dynasty",
        "original": "von Württemberg",
        "translation": "冯 符腾堡",
        "stage": 5,
        "file": "history/countries/WUR - Wurttemberg.txt"
    },
    {
        "key": "1793.10.24|monarch|name",
        "original": "Ludwig Eugen",
        "translation": "路德维希 欧根",
        "stage": 5,
        "file": "history/countries/WUR - Wurttemberg.txt"
    },
    {
        "key": "1793.10.24|monarch|dynasty",
        "original": "von Württemberg",
        "translation": "冯 符腾堡",
        "stage": 5,
        "file": "history/countries/WUR - Wurttemberg.txt"
    },
    {
        "key": "1793.10.24#|heir|name",
        "original": "Friedrich Eugen",
        "translation": "弗里德里希 欧根",
        "stage": 5,
        "file": "history/countries/WUR - Wurttemberg.txt"
    },
    {
        "key": "1793.10.24#|heir|monarch_name",
        "original": "Friedrich II Eugen",
        "translation": "弗里德里希 II 欧根",
        "stage": 5,
        "file": "history/countries/WUR - Wurttemberg.txt"
    },
    {
        "key": "1793.10.24#|heir|dynasty",
        "original": "von Württemberg",
        "translation": "冯 符腾堡",
        "stage": 5,
        "file": "history/countries/WUR - Wurttemberg.txt"
    },
    {
        "key": "1795.5.20|monarch|name",
        "original": "Friedrich II Eugen",
        "translation": "弗里德里希 II 欧根",
        "stage": 5,
        "file": "history/countries/WUR - Wurttemberg.txt"
    },
    {
        "key": "1795.5.20|monarch|dynasty",
        "original": "von Württemberg",
        "translation": "冯 符腾堡",
        "stage": 5,
        "file": "history/countries/WUR - Wurttemberg.txt"
    },
    {
        "key": "1795.5.20#|heir|name",
        "original": "Friedrich",
        "translation": "弗里德里希",
        "stage": 5,
        "file": "history/countries/WUR - Wurttemberg.txt"
    },
    {
        "key": "1795.5.20#|heir|monarch_name",
        "original": "Friedrich I",
        "translation": "弗里德里希 I",
        "stage": 5,
        "file": "history/countries/WUR - Wurttemberg.txt"
    },
    {
        "key": "1795.5.20#|heir|dynasty",
        "original": "von Württemberg",
        "translation": "冯 符腾堡",
        "stage": 5,
        "file": "history/countries/WUR - Wurttemberg.txt"
    },
    {
        "key": "1797.12.22|monarch|name",
        "original": "Friedrich I",
        "translation": "弗里德里希 I",
        "stage": 2,
        "file": "history/countries/WUR - Wurttemberg.txt"
    },
    {
        "key": "1797.12.22|monarch|dynasty",
        "original": "von Württemberg",
        "translation": "冯 符腾堡",
        "stage": 5,
        "file": "history/countries/WUR - Wurttemberg.txt"
    },
    {
        "key": "1797.12.22#|heir|name",
        "original": "William",
        "translation": "威廉",
        "stage": 5,
        "file": "history/countries/WUR - Wurttemberg.txt"
    },
    {
        "key": "1797.12.22#|heir|monarch_name",
        "original": "William I",
        "translation": "威廉 I",
        "stage": 5,
        "file": "history/countries/WUR - Wurttemberg.txt"
    },
    {
        "key": "1797.12.22#|heir|dynasty",
        "original": "von Württemberg",
        "translation": "冯 符腾堡",
        "stage": 5,
        "file": "history/countries/WUR - Wurttemberg.txt"
    },
    {
        "key": "1816.10.30|monarch|name",
        "original": "William I",
        "translation": "威廉 I",
        "stage": 5,
        "file": "history/countries/WUR - Wurttemberg.txt"
    },
    {
        "key": "1816.10.30|monarch|dynasty",
        "original": "von Württemberg",
        "translation": "冯 符腾堡",
        "stage": 5,
        "file": "history/countries/WUR - Wurttemberg.txt"
    }
]