[
    {
        "key": "#KEY#|monarch_names|Ivan #0",
        "original": "Ivan #0",
        "translation": "伊凡 #0",
        "stage": 1
    },
    {
        "key": "#KEY#|monarch_names|Pavlo #0",
        "original": "Pavlo #0",
        "translation": "保罗 #0",
        "stage": 1
    },
    {
        "key": "#KEY#|monarch_names|Bogdan #4",
        "original": "Bogdan #4",
        "translation": "博格丹 #4",
        "stage": 1
    },
    {
        "key": "#KEY#|monarch_names|Danylo #0",
        "original": "Danylo #0",
        "translation": "丹尼尔 #0",
        "stage": 1
    },
    {
        "key": "#KEY#|monarch_names|Kyrilo #0",
        "original": "Kyrilo #0",
        "translation": "西里尔 #0",
        "stage": 1
    },
    {
        "key": "#KEY#|monarch_names|Petro #0",
        "original": "Petro #0",
        "translation": "佩特罗 #0",
        "stage": 1
    },
    {
        "key": "#KEY#|monarch_names|Pylip #0",
        "original": "Pylip #0",
        "translation": "菲利普 #0",
        "stage": 1
    },
    {
        "key": "#KEY#|monarch_names|Stepan #0",
        "original": "Stepan #0",
        "translation": "斯特潘 #0",
        "stage": 1
    },
    {
        "key": "#KEY#|monarch_names|Yuriy #0",
        "original": "Yuriy #0",
        "translation": "尤里 #0",
        "stage": 1
    },
    {
        "key": "#KEY#|monarch_names|Demyan #0",
        "original": "Demyan #0",
        "translation": "季米扬 #0",
        "stage": 1
    },
    {
        "key": "#KEY#|monarch_names|Mykhaylo #0",
        "original": "Mykhaylo #0",
        "translation": "米哈伊洛 #0",
        "stage": 1
    },
    {
        "key": "#KEY#|monarch_names|Dmytro #3",
        "original": "Dmytro #3",
        "translation": "德米特罗 #3",
        "stage": 1
    },
    {
        "key": "#KEY#|monarch_names|Maksym #2",
        "original": "Maksym #2",
        "translation": "马克西姆 #2",
        "stage": 1
    },
    {
        "key": "#KEY#|monarch_names|Sava #1",
        "original": "Sava #1",
        "translation": "萨瓦 #1",
        "stage": 1
    },
    {
        "key": "#KEY#|monarch_names|Vassyl #1",
        "original": "Vassyl #1",
        "translation": "瓦西尔 #1",
        "stage": 1
    },
    {
        "key": "#KEY#|monarch_names|Andriy #0",
        "original": "Andriy #0",
        "translation": "安德烈 #0",
        "stage": 1
    },
    {
        "key": "#KEY#|monarch_names|Bohuslav #0",
        "original": "Bohuslav #0",
        "translation": "博胡斯拉夫 #0",
        "stage": 1
    },
    {
        "key": "#KEY#|monarch_names|Borysko #0",
        "original": "Borysko #0",
        "translation": "博罗夫斯克 #0",
        "stage": 1
    },
    {
        "key": "#KEY#|monarch_names|Boyko #0",
        "original": "Boyko #0",
        "translation": "博伊科 #0",
        "stage": 1
    },
    {
        "key": "#KEY#|monarch_names|Fedir #0",
        "original": "Fedir #0",
        "translation": "费奥多尔 #0",
        "stage": 1
    },
    {
        "key": "#KEY#|monarch_names|Hedeon #0",
        "original": "Hedeon #0",
        "translation": "海德翁 #0",
        "stage": 1
    },
    {
        "key": "#KEY#|monarch_names|Hryhoriy #0",
        "original": "Hryhoriy #0",
        "translation": "格里戈雷 #0",
        "stage": 1
    },
    {
        "key": "#KEY#|monarch_names|Kristiyan #0",
        "original": "Kristiyan #0",
        "translation": "克里斯蒂安 #0",
        "stage": 1
    },
    {
        "key": "#KEY#|monarch_names|Marko #0",
        "original": "Marko #0",
        "translation": "马尔科 #0",
        "stage": 1
    },
    {
        "key": "#KEY#|monarch_names|Matviyko #0",
        "original": "Matviyko #0",
        "translation": "马特维严科 #0",
        "stage": 1
    },
    {
        "key": "#KEY#|monarch_names|Mecheslav #0",
        "original": "Mecheslav #0",
        "translation": "梅切斯拉夫 #0",
        "stage": 1
    },
    {
        "key": "#KEY#|monarch_names|Mykola #0",
        "original": "Mykola #0",
        "translation": "尼古拉 #0",
        "stage": 1
    },
    {
        "key": "#KEY#|monarch_names|Myroslav #0",
        "original": "Myroslav #0",
        "translation": "米罗斯拉夫 #0",
        "stage": 1
    },
    {
        "key": "#KEY#|monarch_names|Nykon #0",
        "original": "Nykon #0",
        "translation": "尼康 #0",
        "stage": 1
    },
    {
        "key": "#KEY#|monarch_names|Olek #0",
        "original": "Olek #0",
        "translation": "奥列克 #0",
        "stage": 1
    },
    {
        "key": "#KEY#|monarch_names|Oleksander #0",
        "original": "Oleksander #0",
        "translation": "亚历山大 #0",
        "stage": 1
    },
    {
        "key": "#KEY#|monarch_names|Oleksiy #0",
        "original": "Oleksiy #0",
        "translation": "奥尔克西  #0",
        "stage": 1
    },
    {
        "key": "#KEY#|monarch_names|Radomyr #0",
        "original": "Radomyr #0",
        "translation": "拉多米尔 #0",
        "stage": 1
    },
    {
        "key": "#KEY#|monarch_names|Svyatoslav #0",
        "original": "Svyatoslav #0",
        "translation": "斯维亚托斯拉夫 #0",
        "stage": 1
    },
    {
        "key": "#KEY#|monarch_names|Symon #0",
        "original": "Symon #0",
        "translation": "西蒙 #0",
        "stage": 1
    },
    {
        "key": "#KEY#|monarch_names|Taras #0",
        "original": "Taras #0",
        "translation": "塔拉斯 #0",
        "stage": 1
    },
    {
        "key": "#KEY#|monarch_names|Volodymyr #0",
        "original": "Volodymyr #0",
        "translation": "弗拉基米尔 #0",
        "stage": 1
    },
    {
        "key": "#KEY#|monarch_names|Yakiv #0",
        "original": "Yakiv #0",
        "translation": "亚契夫 #0",
        "stage": 1
    },
    {
        "key": "#KEY#|monarch_names|Yevhevniy #0",
        "original": "Yevhevniy #0",
        "translation": "叶夫黑夫尼 #0",
        "stage": 1
    },
    {
        "key": "#KEY#|monarch_names|Yosip #0",
        "original": "Yosip #0",
        "translation": "约西普 #0",
        "stage": 1
    },
    {
        "key": "#KEY#|monarch_names|Vladislava #0",
        "original": "Vladislava #0",
        "translation": "弗拉迪斯拉夫 #0",
        "stage": 1
    },
    {
        "key": "#KEY#|monarch_names|Yesfir #0",
        "original": "Yesfir #0",
        "translation": "叶斯菲里 #0",
        "stage": 1
    },
    {
        "key": "#KEY#|monarch_names|Bogdana #0",
        "original": "Bogdana #0",
        "translation": "波格丹纳 #0",
        "stage": 1
    },
    {
        "key": "#LIST#|leader_names|Andrukhovych",
        "original": "Andrukhovych",
        "translation": "安德鲁克维奇",
        "stage": 1
    },
    {
        "key": "#LIST#|leader_names|Cheremshyna",
        "original": "Cheremshyna",
        "translation": "切列姆什娜",
        "stage": 1
    },
    {
        "key": "#LIST#|leader_names|Dukhnovych",
        "original": "Dukhnovych",
        "translation": "杜克诺维奇",
        "stage": 1
    },
    {
        "key": "#LIST#|leader_names|Holovatskyi",
        "original": "Holovatskyi",
        "translation": "霍洛瓦茨基",
        "stage": 1
    },
    {
        "key": "#LIST#|leader_names|Hutsalo",
        "original": "Hutsalo",
        "translation": "胡察罗",
        "stage": 1
    },
    {
        "key": "#LIST#|leader_names|Khvylovy",
        "original": "Khvylovy",
        "translation": "弗维罗威",
        "stage": 1
    },
    {
        "key": "#LIST#|leader_names|Kobylyanska",
        "original": "Kobylyanska",
        "translation": "科贝良斯卡",
        "stage": 1
    },
    {
        "key": "#LIST#|leader_names|Korniychuk",
        "original": "Korniychuk",
        "translation": "科尔尼楚克",
        "stage": 1
    },
    {
        "key": "#LIST#|leader_names|Kostomarov",
        "original": "Kostomarov",
        "translation": "科斯托马罗夫",
        "stage": 1
    },
    {
        "key": "#LIST#|leader_names|Kulish",
        "original": "Kulish",
        "translation": "库利什",
        "stage": 1
    },
    {
        "key": "#LIST#|leader_names|Kvitka",
        "original": "Kvitka",
        "translation": "克维特卡",
        "stage": 1
    },
    {
        "key": "#LIST#|leader_names|Marinina",
        "original": "Marinina",
        "translation": "玛丽尼娜",
        "stage": 1
    },
    {
        "key": "#LIST#|leader_names|Palahniuk",
        "original": "Palahniuk",
        "translation": "帕拉尼克",
        "stage": 1
    },
    {
        "key": "#LIST#|leader_names|Pokalchuk",
        "original": "Pokalchuk",
        "translation": "波卡尔楚克",
        "stage": 1
    },
    {
        "key": "#LIST#|leader_names|Shashkevych",
        "original": "Shashkevych",
        "translation": "沙士凯维奇",
        "stage": 1
    },
    {
        "key": "#LIST#|leader_names|Stefanyk",
        "original": "Stefanyk",
        "translation": "斯捷潘尼克",
        "stage": 1
    },
    {
        "key": "#LIST#|leader_names|Stelmakh",
        "original": "Stelmakh",
        "translation": "斯捷利马赫",
        "stage": 1
    },
    {
        "key": "#LIST#|leader_names|Tobilevich",
        "original": "Tobilevich",
        "translation": "托比列维奇",
        "stage": 1
    },
    {
        "key": "#LIST#|leader_names|Vovchok",
        "original": "Vovchok",
        "translation": "沃夫乔克",
        "stage": 1
    },
    {
        "key": "#LIST#|leader_names|Vyshnia",
        "original": "Vyshnia",
        "translation": "拜什尼亚",
        "stage": 1
    },
    {
        "key": "#LIST#|leader_names|Zabara",
        "original": "Zabara",
        "translation": "萨瓦拉",
        "stage": 1
    },
    {
        "key": "#LIST#|ship_names|Dnieper",
        "original": "Dnieper",
        "translation": "第聂伯河",
        "stage": 1
    },
    {
        "key": "#LIST#|ship_names|Zaporizhia Sich",
        "original": "Zaporizhia Sich",
        "translation": "扎波罗热谢契",
        "stage": 1
    },
    {
        "key": "#LIST#|ship_names|Khortytsia",
        "original": "Khortytsia",
        "translation": "霍尔蒂恰",
        "stage": 1
    },
    {
        "key": "#LIST#|ship_names|Zaporozhian Voisko",
        "original": "Zaporozhian Voisko",
        "translation": "扎波罗热之声",
        "stage": 1
    },
    {
        "key": "#LIST#|ship_names|Orekhov",
        "original": "Orekhov",
        "translation": "奥列霍夫",
        "stage": 1
    },
    {
        "key": "#LIST#|ship_names|Pologi",
        "original": "Pologi",
        "translation": "分娩",
        "stage": 1
    },
    {
        "key": "#LIST#|ship_names|Melitopol",
        "original": "Melitopol",
        "translation": "梅利托波尔",
        "stage": 1
    },
    {
        "key": "#LIST#|ship_names|Energodar",
        "original": "Energodar",
        "translation": "安那荷达",
        "stage": 1
    },
    {
        "key": "#LIST#|ship_names|Mikhaylovka",
        "original": "Mikhaylovka",
        "translation": "米哈伊洛夫卡",
        "stage": 1
    },
    {
        "key": "#LIST#|ship_names|Tokmak",
        "original": "Tokmak",
        "translation": "托克马克",
        "stage": 1
    },
    {
        "key": "#LIST#|ship_names|Akimivka",
        "original": "Akimivka",
        "translation": "阿金夫卡",
        "stage": 1
    },
    {
        "key": "#LIST#|ship_names|Vesele",
        "original": "Vesele",
        "translation": "快活者",
        "stage": 1
    },
    {
        "key": "#LIST#|ship_names|Viliansk",
        "original": "Viliansk",
        "translation": "布良斯克",
        "stage": 1
    },
    {
        "key": "#LIST#|ship_names|Guliajpole",
        "original": "Guliajpole",
        "translation": "古拉普尔",
        "stage": 1
    }
]