[
    {
        "key": "capital",
        "original": "Lenca",
        "translation": "莱安卡",
        "stage": 1,
        "context": null,
        "file": "history/provinces/2640 - Lenca.txt"
    },
    {
        "key": "1525.1.1|capital",
        "original": "Choluteca",
        "translation": "乔卢特卡",
        "stage": 1,
        "context": null,
        "file": "history/provinces/2640 - Lenca.txt"
    },
    {
        "key": "1578.1.1|capital",
        "original": "Tegucigalpa",
        "translation": "特古西加尔巴",
        "stage": 1,
        "context": null,
        "file": "history/provinces/2640 - Lenca.txt"
    }
]