[
    {
        "key": "country_event|trigger|has_ruler",
        "original": "Shah Rukh",
        "translation": "沙哈鲁",
        "stage": 1,
        "file": "events/flavorTIM.txt"
    },
    {
        "key": "country_event|option|hidden_effect|every_country|limit|OR|dynasty",
        "original": "Timurid",
        "translation": "帖木儿",
        "stage": 1,
        "file": "events/flavorTIM.txt"
    },
    {
        "key": "country_event|option|hidden_effect|every_country|limit|OR|any_neighbor_country|dynasty",
        "original": "Timurid",
        "translation": "帖木儿",
        "stage": 1,
        "file": "events/flavorTIM.txt"
    },
    {
        "key": "country_event#|option|hidden_effect|every_country|limit|OR|dynasty",
        "original": "Timurid",
        "translation": "帖木儿",
        "stage": 1,
        "file": "events/flavorTIM.txt"
    },
    {
        "key": "country_event#|option|hidden_effect|every_country|limit|OR|any_neighbor_country|dynasty",
        "original": "Timurid",
        "translation": "帖木儿",
        "stage": 1,
        "file": "events/flavorTIM.txt"
    },
    {
        "key": "country_event##|option|trigger|dynasty",
        "original": "Timurid",
        "translation": "帖木儿",
        "stage": 1,
        "file": "events/flavorTIM.txt"
    },
    {
        "key": "country_event###|trigger|has_ruler",
        "original": "Ulugh Beg",
        "translation": "兀鲁伯",
        "stage": 5,
        "file": "events/flavorTIM.txt"
    },
    {
        "key": "country_event##|option#|trigger|NOT|dynasty",
        "original": "Timurid",
        "translation": "帖木儿",
        "stage": 1,
        "file": "events/flavorTIM.txt"
    },
    {
        "key": "country_event##|option#|if|limit|NOT|dynasty",
        "original": "Timurid",
        "translation": "帖木儿",
        "stage": 1,
        "file": "events/flavorTIM.txt"
    }
]