[
    {
        "key": "#KEY#|monarch_names|Giovanni #0",
        "original": "Giovanni #0",
        "translation": "乔凡尼 #0",
        "stage": 1,
        "context": null,
        "file": "common/countries/Crete.txt"
    },
    {
        "key": "#KEY#|monarch_names|Antonio #0",
        "original": "Antonio #0",
        "translation": "安东尼奥 #0",
        "stage": 1,
        "context": null,
        "file": "common/countries/Crete.txt"
    },
    {
        "key": "#KEY#|monarch_names|Giacomo #0",
        "original": "Giacomo #0",
        "translation": "贾科莫 #0",
        "stage": 1,
        "context": null,
        "file": "common/countries/Crete.txt"
    },
    {
        "key": "#KEY#|monarch_names|Girolamo #0",
        "original": "Girolamo #0",
        "translation": "吉罗拉莫 #0",
        "stage": 1,
        "context": null,
        "file": "common/countries/Crete.txt"
    },
    {
        "key": "#KEY#|monarch_names|Francesco #0",
        "original": "Francesco #0",
        "translation": "弗朗切斯科 #0",
        "stage": 1,
        "context": null,
        "file": "common/countries/Crete.txt"
    },
    {
        "key": "#KEY#|monarch_names|Benedetto #0",
        "original": "Benedetto #0",
        "translation": "贝内代托 #0",
        "stage": 1,
        "context": null,
        "file": "common/countries/Crete.txt"
    },
    {
        "key": "#KEY#|monarch_names|Bernardo #0",
        "original": "Bernardo #0",
        "translation": "贝尔纳多 #0",
        "stage": 1,
        "context": null,
        "file": "common/countries/Crete.txt"
    },
    {
        "key": "#KEY#|monarch_names|Domenico #0",
        "original": "Domenico #0",
        "translation": "多梅尼科 #0",
        "stage": 1,
        "context": null,
        "file": "common/countries/Crete.txt"
    },
    {
        "key": "#KEY#|monarch_names|Donato #0",
        "original": "Donato #0",
        "translation": "多纳托 #0",
        "stage": 1,
        "context": null,
        "file": "common/countries/Crete.txt"
    },
    {
        "key": "#KEY#|monarch_names|Ferdinando #0",
        "original": "Ferdinando #0",
        "translation": "费迪南多 #0",
        "stage": 1,
        "context": null,
        "file": "common/countries/Crete.txt"
    },
    {
        "key": "#KEY#|monarch_names|Giuseppe #0",
        "original": "Giuseppe #0",
        "translation": "朱塞佩 #0",
        "stage": 1,
        "context": null,
        "file": "common/countries/Crete.txt"
    },
    {
        "key": "#KEY#|monarch_names|Lazzaro #0",
        "original": "Lazzaro #0",
        "translation": "拉扎罗 #0",
        "stage": 1,
        "context": null,
        "file": "common/countries/Crete.txt"
    },
    {
        "key": "#KEY#|monarch_names|Lodovico #0",
        "original": "Lodovico #0",
        "translation": "洛多维科 #0",
        "stage": 1,
        "context": null,
        "file": "common/countries/Crete.txt"
    },
    {
        "key": "#KEY#|monarch_names|Marco #0",
        "original": "Marco #0",
        "translation": "马可 #0",
        "stage": 1,
        "context": null,
        "file": "common/countries/Crete.txt"
    },
    {
        "key": "#KEY#|monarch_names|Paolo Antonio #0",
        "original": "Paolo Antonio #0",
        "translation": "保罗 安东尼奥 #0",
        "stage": 1,
        "context": null,
        "file": "common/countries/Crete.txt"
    },
    {
        "key": "#KEY#|monarch_names|Pasquale #0",
        "original": "Pasquale #0",
        "translation": "帕斯卡尔 #0",
        "stage": 1,
        "context": null,
        "file": "common/countries/Crete.txt"
    },
    {
        "key": "#KEY#|monarch_names|Pierluigi #0",
        "original": "Pierluigi #0",
        "translation": "皮耶路易吉 #0",
        "stage": 1,
        "context": null,
        "file": "common/countries/Crete.txt"
    },
    {
        "key": "#KEY#|monarch_names|Zaccaria #0",
        "original": "Zaccaria #0",
        "translation": "扎卡里亚 #0",
        "stage": 1,
        "context": null,
        "file": "common/countries/Crete.txt"
    },
    {
        "key": "#KEY#|monarch_names|Paolo #0",
        "original": "Paolo #0",
        "translation": "保罗 #0",
        "stage": 1,
        "context": null,
        "file": "common/countries/Crete.txt"
    },
    {
        "key": "#KEY#|monarch_names|Pietro #0",
        "original": "Pietro #0",
        "translation": "彼得罗 #0",
        "stage": 1,
        "context": null,
        "file": "common/countries/Crete.txt"
    },
    {
        "key": "#KEY#|monarch_names|Tomasso #0",
        "original": "Tomasso #0",
        "translation": "托马索 #0",
        "stage": 1,
        "context": null,
        "file": "common/countries/Crete.txt"
    },
    {
        "key": "#KEY#|monarch_names|Andrea #0",
        "original": "Andrea #0",
        "translation": "安德里亚 #0",
        "stage": 1,
        "context": null,
        "file": "common/countries/Crete.txt"
    },
    {
        "key": "#KEY#|monarch_names|Leonardo #0",
        "original": "Leonardo #0",
        "translation": "莱奥纳尔多 #0",
        "stage": 1,
        "context": null,
        "file": "common/countries/Crete.txt"
    },
    {
        "key": "#KEY#|monarch_names|Aiolos #0",
        "original": "Aiolos #0",
        "translation": "艾洛斯 #0",
        "stage": 1,
        "context": null,
        "file": "common/countries/Crete.txt"
    },
    {
        "key": "#KEY#|monarch_names|Bartholomaios #0",
        "original": "Bartholomaios #0",
        "translation": "巴尔托洛迈奥斯 #0",
        "stage": 1,
        "context": null,
        "file": "common/countries/Crete.txt"
    },
    {
        "key": "#KEY#|monarch_names|Dionysios #0",
        "original": "Dionysios #0",
        "translation": "狄奥尼修斯 #0",
        "stage": 1,
        "context": null,
        "file": "common/countries/Crete.txt"
    },
    {
        "key": "#KEY#|monarch_names|Eusebios #0",
        "original": "Eusebios #0",
        "translation": "尤塞比奥斯 #0",
        "stage": 1,
        "context": null,
        "file": "common/countries/Crete.txt"
    },
    {
        "key": "#KEY#|monarch_names|Gregorios #0",
        "original": "Gregorios #0",
        "translation": "格里高利 #0",
        "stage": 1,
        "context": null,
        "file": "common/countries/Crete.txt"
    },
    {
        "key": "#KEY#|monarch_names|Hermogenes #0",
        "original": "Hermogenes #0",
        "translation": "赫尔墨格涅斯 #0",
        "stage": 1,
        "context": null,
        "file": "common/countries/Crete.txt"
    },
    {
        "key": "#KEY#|monarch_names|Ioannes #0",
        "original": "Ioannes #0",
        "translation": "约安尼斯 #0",
        "stage": 1,
        "context": null,
        "file": "common/countries/Crete.txt"
    },
    {
        "key": "#KEY#|monarch_names|Konstantinos #0",
        "original": "Konstantinos #0",
        "translation": "君士坦丁 #0",
        "stage": 1,
        "context": null,
        "file": "common/countries/Crete.txt"
    },
    {
        "key": "#KEY#|monarch_names|Kreon #0",
        "original": "Kreon #0",
        "translation": "科雷昂 #0",
        "stage": 1,
        "context": null,
        "file": "common/countries/Crete.txt"
    },
    {
        "key": "#KEY#|monarch_names|Lavrentios #0",
        "original": "Lavrentios #0",
        "translation": "劳伦提奥斯 #0",
        "stage": 1,
        "context": null,
        "file": "common/countries/Crete.txt"
    },
    {
        "key": "#KEY#|monarch_names|Matthaios #0",
        "original": "Matthaios #0",
        "translation": "马太奥斯 #0",
        "stage": 1,
        "context": null,
        "file": "common/countries/Crete.txt"
    },
    {
        "key": "#KEY#|monarch_names|Nikolaos #0",
        "original": "Nikolaos #0",
        "translation": "尼科劳斯 #0",
        "stage": 1,
        "context": null,
        "file": "common/countries/Crete.txt"
    },
    {
        "key": "#KEY#|monarch_names|Nikomachos #0",
        "original": "Nikomachos #0",
        "translation": "尼科马科斯 #0",
        "stage": 1,
        "context": null,
        "file": "common/countries/Crete.txt"
    },
    {
        "key": "#KEY#|monarch_names|Nomiki #0",
        "original": "Nomiki #0",
        "translation": "诺米基 #0",
        "stage": 1,
        "context": null,
        "file": "common/countries/Crete.txt"
    },
    {
        "key": "#KEY#|monarch_names|Serafeim #0",
        "original": "Serafeim #0",
        "translation": "塞拉菲姆 #0",
        "stage": 1,
        "context": null,
        "file": "common/countries/Crete.txt"
    },
    {
        "key": "#KEY#|monarch_names|Spyridon #0",
        "original": "Spyridon #0",
        "translation": "斯皮里东 #0",
        "stage": 1,
        "context": null,
        "file": "common/countries/Crete.txt"
    },
    {
        "key": "#KEY#|monarch_names|Theodoros #0",
        "original": "Theodoros #0",
        "translation": "狄奥多罗斯 #0",
        "stage": 1,
        "context": null,
        "file": "common/countries/Crete.txt"
    },
    {
        "key": "#KEY#|monarch_names|Elpida #0",
        "original": "Elpida #0",
        "translation": "伊尔比达 #0",
        "stage": 1,
        "context": null,
        "file": "common/countries/Crete.txt"
    },
    {
        "key": "#KEY#|monarch_names|Kyriake #0",
        "original": "Kyriake #0",
        "translation": "希利蕾吉 #0",
        "stage": 1,
        "context": null,
        "file": "common/countries/Crete.txt"
    },
    {
        "key": "#KEY#|monarch_names|Thekla #0",
        "original": "Thekla #0",
        "translation": "狄卡拉 #0",
        "stage": 1,
        "context": null,
        "file": "common/countries/Crete.txt"
    },
    {
        "key": "#LIST#|ship_names|Dermoaros",
        "original": "Dermoaros",
        "translation": "德莫亚洛斯",
        "stage": 1,
        "context": null,
        "file": "common/countries/Crete.txt"
    },
    {
        "key": "#LIST#|ship_names|Frangokastelo",
        "original": "Frangokastelo",
        "translation": "弗朗哥卡斯特隆",
        "stage": 1,
        "context": null,
        "file": "common/countries/Crete.txt"
    },
    {
        "key": "#LIST#|ship_names|Glalos",
        "original": "Glalos",
        "translation": "格拉罗斯",
        "stage": 1,
        "context": null,
        "file": "common/countries/Crete.txt"
    },
    {
        "key": "#LIST#|ship_names|Koudouras",
        "original": "Koudouras",
        "translation": "孔杜拉斯",
        "stage": 1,
        "context": null,
        "file": "common/countries/Crete.txt"
    },
    {
        "key": "#LIST#|ship_names|Lentas",
        "original": "Lentas",
        "translation": "兰特斯",
        "stage": 1,
        "context": null,
        "file": "common/countries/Crete.txt"
    },
    {
        "key": "#LIST#|ship_names|Matala",
        "original": "Matala",
        "translation": "马塔拉",
        "stage": 1,
        "context": null,
        "file": "common/countries/Crete.txt"
    },
    {
        "key": "#LIST#|ship_names|Paleochora",
        "original": "Paleochora",
        "translation": "帕雷欧霍拉",
        "stage": 1,
        "context": null,
        "file": "common/countries/Crete.txt"
    },
    {
        "key": "#LIST#|ship_names|Papadogiannis",
        "original": "Papadogiannis",
        "translation": "帕帕佐扬尼斯",
        "stage": 1,
        "context": null,
        "file": "common/countries/Crete.txt"
    },
    {
        "key": "#LIST#|ship_names|Plakias",
        "original": "Plakias",
        "translation": "普拉基亚斯",
        "stage": 1,
        "context": null,
        "file": "common/countries/Crete.txt"
    },
    {
        "key": "#LIST#|ship_names|Sougia",
        "original": "Sougia",
        "translation": "苏吉亚",
        "stage": 1,
        "context": null,
        "file": "common/countries/Crete.txt"
    },
    {
        "key": "#LIST#|leader_names|Argyrus",
        "original": "Argyrus",
        "translation": "阿尔吉鲁斯",
        "stage": 1,
        "context": null,
        "file": "common/countries/Crete.txt"
    },
    {
        "key": "#LIST#|leader_names|Artavasdus",
        "original": "Artavasdus",
        "translation": "阿尔塔瓦兹德",
        "stage": 1,
        "context": null,
        "file": "common/countries/Crete.txt"
    },
    {
        "key": "#LIST#|leader_names|Basileus",
        "original": "Basileus",
        "translation": "巴西琉斯",
        "stage": 1,
        "context": null,
        "file": "common/countries/Crete.txt"
    },
    {
        "key": "#LIST#|leader_names|Diogenes",
        "original": "Diogenes",
        "translation": "第欧根尼",
        "stage": 1,
        "context": null,
        "file": "common/countries/Crete.txt"
    },
    {
        "key": "#LIST#|leader_names|Ducas",
        "original": "Ducas",
        "translation": "杜卡斯",
        "stage": 1,
        "context": null,
        "file": "common/countries/Crete.txt"
    },
    {
        "key": "#LIST#|leader_names|Monomachus",
        "original": "Monomachus",
        "translation": "莫诺马霍斯",
        "stage": 1,
        "context": null,
        "file": "common/countries/Crete.txt"
    },
    {
        "key": "#LIST#|leader_names|Morosini",
        "original": "Morosini",
        "translation": "莫罗西尼",
        "stage": 1,
        "context": null,
        "file": "common/countries/Crete.txt"
    },
    {
        "key": "#LIST#|leader_names|Romanus",
        "original": "Romanus",
        "translation": "罗马努斯",
        "stage": 1,
        "context": null,
        "file": "common/countries/Crete.txt"
    },
    {
        "key": "#LIST#|leader_names|Stauracius",
        "original": "Stauracius",
        "translation": "斯陶拉基奥斯",
        "stage": 1,
        "context": null,
        "file": "common/countries/Crete.txt"
    },
    {
        "key": "#LIST#|leader_names|Stratioticus",
        "original": "Stratioticus",
        "translation": "斯特拉提奥提库斯",
        "stage": 1,
        "context": null,
        "file": "common/countries/Crete.txt"
    },
    {
        "key": "#LIST#|leader_names|Vataces",
        "original": "Vataces",
        "translation": "瓦塔西斯",
        "stage": 1,
        "context": null,
        "file": "common/countries/Crete.txt"
    },
    {
        "key": "#LIST#|leader_names|de Vendôme",
        "original": "de Vendôme",
        "translation": "德 旺多姆",
        "stage": 1,
        "context": null,
        "file": "common/countries/Crete.txt"
    },
    {
        "key": "#LIST#|leader_names|Zimisces",
        "original": "Zimisces",
        "translation": "齐米谢斯",
        "stage": 1,
        "context": null,
        "file": "common/countries/Crete.txt"
    }
]